data_ingestion.py
main.py
nonstandardcode.py
preprocessing.py
scoring.py
training.py
python_project_uv-0.2.0.dist-info/METADATA
python_project_uv-0.2.0.dist-info/WHEEL
python_project_uv-0.2.0.dist-info/top_level.txt
python_project_uv-0.2.0.dist-info/RECORD
