Metadata-Version: 2.4
Name: python-project-uv
Version: 0.2.0
Summary: Add your description here
Requires-Python: >=3.12
Requires-Dist: numpy==1.26.4
Requires-Dist: pandas>=2.2.3
Requires-Dist: scikit-learn>=1.6.1
Requires-Dist: six>=1.17.0
Provides-Extra: formatter
Requires-Dist: black; extra == "formatter"
Requires-Dist: isort; extra == "formatter"
Requires-Dist: flake8; extra == "formatter"
Provides-Extra: plot
Requires-Dist: matplotlib; extra == "plot"
Requires-Dist: seaborn; extra == "plot"
Provides-Extra: test
Requires-Dist: pytest; extra == "test"
